churn/__init__.py
churn/__main__.py
churn/batch.py
churn/configurator.py
churn/task.py
python_churn-1.1.2.dist-info/METADATA
python_churn-1.1.2.dist-info/WHEEL
python_churn-1.1.2.dist-info/licenses/LICENSE
python_churn-1.1.2.dist-info/RECORD
