Metadata-Version: 2.4
Name: python-churn
Version: 1.1.2
Summary: CHAin sluRM is a simple batch job runner.
License-Expression: MIT
License-File: LICENSE
Classifier: Operating System :: OS Independent
Classifier: Programming Language :: Python :: 3
Requires-Python: >=3.10
Requires-Dist: jinja2>=3.1.6
Requires-Dist: pyyaml>=6.0.2
